screenplain/__init__.py
screenplain/main.py
screenplain/richstring.py
screenplain/types.py
screenplain/export/__init__.py
screenplain/export/default.css
screenplain/export/fdx.py
screenplain/export/html.py
screenplain/export/pdf.py
screenplain/parsers/__init__.py
screenplain/parsers/fountain.py
screenplain-0.9.0.data/scripts/screenplain
screenplain-0.9.0.dist-info/LICENSE.txt
screenplain-0.9.0.dist-info/METADATA
screenplain-0.9.0.dist-info/WHEEL
screenplain-0.9.0.dist-info/top_level.txt
screenplain-0.9.0.dist-info/RECORD
